roiextract/__init__.py
roiextract/analytic.py
roiextract/filter.py
roiextract/numerical.py
roiextract/optimize.py
roiextract/quantify.py
roiextract/utils.py
roiextract-0.0.3.dist-info/METADATA
roiextract-0.0.3.dist-info/WHEEL
roiextract-0.0.3.dist-info/licenses/LICENSE
roiextract-0.0.3.dist-info/RECORD
