Metadata-Version: 2.3
Name: roiextract
Version: 0.0.3
Summary: Data-independent and data-driven optimization of spatial filters for extraction of ROI time series based on M/EEG
Project-URL: Homepage, https://github.com/ctrltz/roiextract
Project-URL: Bug Tracker, https://github.com/ctrltz/roiextract/issues
Author-email: Nikolai Kapralov <kapralov@cbs.mpg.de>
License-File: LICENSE
Classifier: License :: OSI Approved :: MIT License
Classifier: Operating System :: OS Independent
Classifier: Programming Language :: Python :: 3
Requires-Python: >=3.7
Requires-Dist: mne
Requires-Dist: numpy
Requires-Dist: scipy
